<contactNumber>706341</contactNumber><contactVendorNumber>706341</contactVendorNumber><K/I>I</K/I><contactName>Fischer GmbH Autohaus</contactName><contactAddressStreet>An der Aufstiegstraße 1</contactAddressStreet><contactAddressZipCode>73734</contactAddressZipCode><contactAddressCity>Esslingen am Neckar</contactAddressCity><contactAddressCountry>Deutschland</contactAddressCountry><contactTelephoneNumber>+49 711 34530-3</contactTelephoneNumber><contactFaxNumber>+49 711 3453-55</contactFaxNumber><contactEmail>info@autohaus-fischer.de</contactEmail><contactVATidNumber>DE 813619988</contactVATidNumber><Kurzbezeichnung>Fischer GmbH Au</Kurzbezeichnung><contactCustomerNumber>127591</contactCustomerNumber><contactBank>VB Kirchheim-Nürtingen</contactBank><contactBankNumber>61290120</contactBankNumber><contactBankAccountNumber>25124005</contactBankAccountNumber><contactIBAN>DE37 6129 0120 0025 1240 05</contactIBAN>