<contactNumber>706022</contactNumber><contactVendorNumber>706022</contactVendorNumber><K/I>I</K/I><contactName>Friedrich-Ebert-Schule</contactName><contactAddressStreet>Steinbeisstraße 17</contactAddressStreet><contactAddressZipCode>73730</contactAddressZipCode><contactAddressCity>Esslingen am Neckar</contactAddressCity><contactAddressCountry>Deutschland</contactAddressCountry><contactTelephoneNumber>+49 711 3607-100</contactTelephoneNumber><contactFaxNumber>+49 711 3607-102</contactFaxNumber><contactEmail>info@fes-es.de</contactEmail><Kurzbezeichnung>Friedrich-Ebert</Kurzbezeichnung><contactBank>Kr Spk Esslingen-Nürtingen</contactBank><contactBankNumber>61150020</contactBankNumber><contactBankAccountNumber>900021</contactBankAccountNumber><contactIBAN>DE26 6115 0020 0000 9000 21</contactIBAN>