<contactNumber>710041</contactNumber><contactVendorNumber>710041</contactVendorNumber><K/I>I</K/I><contactName>K & P  GmbH</contactName><contactAddressStreet>Robert-Bosch-Str. 5</contactAddressStreet><contactAddressZipCode>72810</contactAddressZipCode><contactAddressCity>Gomaringen</contactAddressCity><contactAddressCountry>Deutschland</contactAddressCountry><contactTelephoneNumber>+49 7072 131334-3</contactTelephoneNumber><contactFaxNumber>+49 7072 131334-5</contactFaxNumber><contactEmail>info@kup-automation.de</contactEmail><contactVATidNumber>DE 128671379</contactVATidNumber><contactTAXidNumber>86114/69403</contactTAXidNumber><Kurzbezeichnung>K & P  GmbH</Kurzbezeichnung><contactCustomerNumber>10.550</contactCustomerNumber><contactBank>Commerzbank Esslingen</contactBank><contactBankNumber>61140071</contactBankNumber><contactBankAccountNumber>828357400</contactBankAccountNumber><contactIBAN>DE44 6114 0071 0828 3574 00</contactIBAN>