<contactNumber>707061</contactNumber><contactVendorNumber>707061</contactVendorNumber><K/I>I</K/I><contactName>Grözinger GmbH</contactName><contactAddressStreet>Keplerstrasse 8</contactAddressStreet><contactAddressZipCode>73779</contactAddressZipCode><contactAddressCity>Deizisau</contactAddressCity><contactAddressCountry>Deutschland</contactAddressCountry><contactTelephoneNumber>+49 7153 82504-0</contactTelephoneNumber><contactFaxNumber>+49 7153 82504-15</contactFaxNumber><contactEmail>zentrale@groezinger-gmbh.de</contactEmail><contactVATidNumber>DE 147851880</contactVATidNumber><contactTAXidNumber>59311/06455</contactTAXidNumber><Kurzbezeichnung>Grözinger GmbH</Kurzbezeichnung><contactCustomerNumber>27031</contactCustomerNumber><contactBank>Volksbank Plochingen</contactBank><contactBankNumber>61191310</contactBankNumber><contactBankAccountNumber>710420005</contactBankAccountNumber><contactIBAN>DE43 6119 1310 0710 4200 05</contactIBAN>