<contactNumber>702441</contactNumber><contactVendorNumber>702441</contactVendorNumber><K/I>I</K/I><contactName>B Industriebedarf & Dienstleistung</contactName><contactAddressStreet>Eichhornweg 7</contactAddressStreet><contactAddressZipCode>73527</contactAddressZipCode><contactAddressCity>Schwäbisch Gmünd</contactAddressCity><contactAddressCountry>Deutschland</contactAddressCountry><contactTelephoneNumber>+49 7171 9972433</contactTelephoneNumber><contactFaxNumber>+49 7171 9972434</contactFaxNumber><contactTAXidNumber>83391/19809</contactTAXidNumber><Kurzbezeichnung>B Industriebeda</Kurzbezeichnung><contactCustomerNumber>22087</contactCustomerNumber><contactBank>Kreissparkasse Ostalb</contactBank><contactBankNumber>61450050</contactBankNumber><contactBankAccountNumber>1001001069</contactBankAccountNumber><contactIBAN>DE28 6145 0050 1001 0010 69</contactIBAN>