<contactNumber>712381</contactNumber><contactVendorNumber>712381</contactVendorNumber><K/I>I</K/I><contactName>Me-Tec GmbH</contactName><contactAddressStreet>Maybachstraße 4</contactAddressStreet><contactAddressZipCode>71272</contactAddressZipCode><contactAddressCity>Renningen</contactAddressCity><contactAddressCountry>Deutschland</contactAddressCountry><contactTelephoneNumber>+49 7159 9317-0</contactTelephoneNumber><contactFaxNumber>+49 7159 9317-17</contactFaxNumber><contactEmail>info@me-tec-gmbh.de</contactEmail><contactVATidNumber>DE 190590038</contactVATidNumber><Kurzbezeichnung>Me-Tec GmbH</Kurzbezeichnung><contactCustomerNumber>50018</contactCustomerNumber><contactBank>Volksbank Region Leonberg</contactBank><contactBankNumber>60390300</contactBankNumber><contactBankAccountNumber>73274003</contactBankAccountNumber><contactIBAN>DE29 6039 0300 0073 2740 03</contactIBAN>