<contactNumber>720402</contactNumber><contactVendorNumber>720402</contactVendorNumber><K/I>I</K/I><contactName>Thierbach, J. Auto & Motorrad-Service</contactName><contactAddressStreet>Boschstraße 1</contactAddressStreet><contactAddressZipCode>73734</contactAddressZipCode><contactAddressCity>Esslingen</contactAddressCity><contactAddressCountry>Deutschland</contactAddressCountry><contactTelephoneNumber>+49 711 3880073</contactTelephoneNumber><contactFaxNumber>+49 711 3880075</contactFaxNumber><contactVATidNumber>DE 198035892</contactVATidNumber><Kurzbezeichnung>Thierbach, J. A</Kurzbezeichnung><contactCustomerNumber>1127</contactCustomerNumber><contactBank>Kr Spk Esslingen-Nürtingen</contactBank><contactBankNumber>61150020</contactBankNumber><contactBankAccountNumber>8495497</contactBankAccountNumber><contactIBAN>DE59 6115 0020 0008 4954 97</contactIBAN>