<contactNumber>704132</contactNumber><contactVendorNumber>704132</contactVendorNumber><K/I>I</K/I><contactName>DFS Deutsche Flugsicherung GmbH</contactName><contactAddressStreet>Am DFS-Campus 10</contactAddressStreet><contactAddressZipCode>63225</contactAddressZipCode><contactAddressCity>Langen (Hessen)</contactAddressCity><contactAddressCountry>Deutschland</contactAddressCountry><contactTelephoneNumber>+49 6103 707-0</contactTelephoneNumber><contactFaxNumber>+49 6103 707-1396</contactFaxNumber><contactEmail>gebuehren@dfs.de</contactEmail><contactVATidNumber>DE 114110232</contactVATidNumber><Kurzbezeichnung>DFS Deutsche Fl</Kurzbezeichnung><contactCustomerNumber>399471</contactCustomerNumber><contactBank>Deutsche Bank</contactBank><contactBankNumber>50070010</contactBankNumber><contactBankAccountNumber>91673400</contactBankAccountNumber><contactIBAN>DE66 5007 0010 0091 6734 00</contactIBAN>