<contactNumber>701911</contactNumber><contactVendorNumber>701911</contactVendorNumber><K/I>I</K/I><contactName>ARTeco Christine Eichhorn</contactName><contactAddressStreet>Blumenstraße 1</contactAddressStreet><contactAddressZipCode>96277</contactAddressZipCode><contactAddressCity>Schneckenlohe</contactAddressCity><contactAddressCountry>Deutschland</contactAddressCountry><contactTelephoneNumber>+49 9266 991536</contactTelephoneNumber><contactFaxNumber>+49 9266 9919800</contactFaxNumber><contactEmail>info@arteco-online.de</contactEmail><contactVATidNumber>DE 229358756</contactVATidNumber><Kurzbezeichnung>ARTeco Christin</Kurzbezeichnung><contactCustomerNumber>33091</contactCustomerNumber><contactBank>Postbank Nürnberg</contactBank><contactBankNumber>76010085</contactBankNumber><contactBankAccountNumber>393680851</contactBankAccountNumber><contactIBAN>DE87 7601 0085 0393 6808 51</contactIBAN>