<contactNumber>722141</contactNumber><contactVendorNumber>722141</contactVendorNumber><K/I>I</K/I><contactName>Vierheilig Metall-und Stahlbau GmbH</contactName><contactAddressStreet>Neumühle 2</contactAddressStreet><contactAddressZipCode>97727</contactAddressZipCode><contactAddressCity>Fuchsstadt</contactAddressCity><contactAddressCountry>Deutschland</contactAddressCountry><contactTelephoneNumber>+49 9732 780204</contactTelephoneNumber><contactFaxNumber>+49 9732 7830033</contactFaxNumber><contactEmail>mail@metallbau-vierheilig.de</contactEmail><contactVATidNumber>DE 316023582</contactVATidNumber><Kurzbezeichnung>Vierheilig Meta</Kurzbezeichnung><contactCustomerNumber>63</contactCustomerNumber><contactBank>Bank Schilling & Co</contactBank><contactBankNumber>79032038</contactBankNumber><contactBankAccountNumber>33764002</contactBankAccountNumber><contactIBAN>DE73 7903 2038 0033 7640 02</contactIBAN>