<contactNumber>710881</contactNumber><contactVendorNumber>710881</contactVendorNumber><K/I>I</K/I><contactName>Kölle, Wilhelm GmbH</contactName><contactAddressStreet>Industriestr. 35</contactAddressStreet><contactAddressZipCode>74357</contactAddressZipCode><contactAddressCity>Bönnigheim</contactAddressCity><contactAddressCountry>Deutschland</contactAddressCountry><contactTelephoneNumber>+49 7143 407122</contactTelephoneNumber><contactFaxNumber>+49 7143 407124</contactFaxNumber><contactVATidNumber>DE 144993930</contactVATidNumber><Kurzbezeichnung>Kölle, Wilhelm</Kurzbezeichnung><contactCustomerNumber>26925</contactCustomerNumber><contactBank>VR-Bank Neckar-Enz</contactBank><contactBankNumber>60491430</contactBankNumber><contactBankAccountNumber>472571001</contactBankAccountNumber><contactIBAN>DE28 6049 1430 0472 5710 01</contactIBAN>