<contactNumber>712311</contactNumber><contactVendorNumber>712311</contactVendorNumber><K/I>I</K/I><contactName>MBJ Fassadentechnik GmbH</contactName><contactAddressStreet>Am Bahndamm 7</contactAddressStreet><contactAddressZipCode>87677</contactAddressZipCode><contactAddressCity>Stöttwang-Linden</contactAddressCity><contactAddressCountry>Deutschland</contactAddressCountry><contactTelephoneNumber>+49 8345 9528-0</contactTelephoneNumber><contactFaxNumber>+49 8345 9528-29</contactFaxNumber><contactEmail>info@mbj-fassadentechnik.de</contactEmail><contactVATidNumber>DE 275311115</contactVATidNumber><Kurzbezeichnung>MBJ Fassadentec</Kurzbezeichnung><contactCustomerNumber>1123</contactCustomerNumber><contactBank>Augusta-Bank RVB Augsburg</contactBank><contactBankNumber>72090000</contactBankNumber><contactBankAccountNumber>816779</contactBankAccountNumber><contactIBAN>DE18 7209 0000 0000 8167 79</contactIBAN>