<contactNumber>720061</contactNumber><contactVendorNumber>720061</contactVendorNumber><K/I>I</K/I><contactName>Tools & Systems GmbH & Co. KG - unvollst</contactName><contactAddressStreet>Wilhelm-Frank-Straße 45</contactAddressStreet><contactAddressZipCode>74564</contactAddressZipCode><contactAddressCity>Crailsheim</contactAddressCity><contactAddressCountry>Deutschland</contactAddressCountry><contactTelephoneNumber>+49 7951 4699036</contactTelephoneNumber><contactFaxNumber>+49 7951 4699037</contactFaxNumber><Kurzbezeichnung>Tools & Systems</Kurzbezeichnung>