<contactNumber>716122</contactNumber><contactVendorNumber>716122</contactVendorNumber><K/I>I</K/I><contactName>RUD Ketten Rieger & Dietz GmbH u. Co. KG</contactName><contactAddressStreet>Friedensinsel</contactAddressStreet><contactAddressZipCode>73432</contactAddressZipCode><contactAddressCity>Aalen</contactAddressCity><contactAddressCountry>Deutschland</contactAddressCountry><contactTelephoneNumber>+49 7361 504-0</contactTelephoneNumber><contactFaxNumber>+49 7361 504-1450</contactFaxNumber><contactVATidNumber>DE 144651102</contactVATidNumber><Kurzbezeichnung>RUD Ketten Rieg</Kurzbezeichnung><contactCustomerNumber>23516</contactCustomerNumber><contactBank>LBBW/BW-Bank Stuttgart</contactBank><contactBankNumber>60050101</contactBankNumber><contactBankAccountNumber>4201094</contactBankAccountNumber><contactIBAN>DE88 6005 0101 0004 2010 94</contactIBAN>