<contactNumber>715022</contactNumber><contactVendorNumber>715022</contactVendorNumber><K/I>I</K/I><contactName>Quacert GmbH</contactName><contactAddressStreet>Eutighoferstr. 137</contactAddressStreet><contactAddressZipCode>73525</contactAddressZipCode><contactAddressCity>Schwäbisch Gmünd</contactAddressCity><contactAddressCountry>Deutschland</contactAddressCountry><contactTelephoneNumber>+49 7171 99791640</contactTelephoneNumber><contactFaxNumber>+49 7171 929353</contactFaxNumber><contactEmail>info@quacert.de</contactEmail><contactVATidNumber>DE 174358762</contactVATidNumber><contactTAXidNumber>83088/14899</contactTAXidNumber><Kurzbezeichnung>Quacert GmbH</Kurzbezeichnung><contactCustomerNumber>99/12</contactCustomerNumber><contactBank>Kreissparkasse Ostalb</contactBank><contactBankNumber>61450050</contactBankNumber><contactBankAccountNumber>440585927</contactBankAccountNumber><contactIBAN>DE91 6145 0050 0440 5859 27</contactIBAN>