<contactNumber>723372</contactNumber><contactVendorNumber>723372</contactVendorNumber><K/I>I</K/I><contactName>Winkel GmbH</contactName><contactAddressStreet>Am Illinger Eck 7</contactAddressStreet><contactAddressZipCode>75428</contactAddressZipCode><contactAddressCity>Illingen</contactAddressCity><contactAddressCountry>Deutschland</contactAddressCountry><contactTelephoneNumber>+49 7042 8250-0</contactTelephoneNumber><contactFaxNumber>+49 7042 23888</contactFaxNumber><contactEmail>winkel@winkel.de</contactEmail><contactVATidNumber>DE 144525771</contactVATidNumber><contactTAXidNumber>48022/00849</contactTAXidNumber><Kurzbezeichnung>Winkel GmbH</Kurzbezeichnung><contactCustomerNumber>19590</contactCustomerNumber><contactBank>Deutsche Bank PGK Pforzheim</contactBank><contactBankNumber>66670024</contactBankNumber><contactBankAccountNumber>30777700</contactBankAccountNumber><contactIBAN>DE91 6667 0024 0030 7777 00</contactIBAN>