<contactNumber>710551</contactNumber><contactVendorNumber>710551</contactVendorNumber><K/I>I</K/I><contactName>Knauer Packsysteme e.K.</contactName><contactAddressStreet>Blütenweg 4</contactAddressStreet><contactAddressZipCode>87448</contactAddressZipCode><contactAddressCity>Waltenhofen-Oberdorf</contactAddressCity><contactAddressCountry>Deutschland</contactAddressCountry><contactTelephoneNumber>+49 8379 929983</contactTelephoneNumber><contactFaxNumber>+49 8379 929984</contactFaxNumber><contactEmail>office@knauer.cc</contactEmail><contactVATidNumber>DE 811750308</contactVATidNumber><contactTAXidNumber>127 237 40191</contactTAXidNumber><Kurzbezeichnung>Knauer Packsyst</Kurzbezeichnung><contactCustomerNumber>102559</contactCustomerNumber><contactBank>Sparkasse Allgäu</contactBank><contactBankNumber>73350000</contactBankNumber><contactBankAccountNumber>310006796</contactBankAccountNumber><contactIBAN>DE73 7335 0000 0310 0067 96</contactIBAN>