<contactNumber>702011</contactNumber><contactVendorNumber>702011</contactVendorNumber><K/I>I</K/I><contactName>Brielmann, Bernd Auto-Kran-Betrieb</contactName><contactAddressStreet>Siemensstr. 15-17</contactAddressStreet><contactAddressZipCode>72116</contactAddressZipCode><contactAddressCity>Mössingen</contactAddressCity><contactAddressCountry>Deutschland</contactAddressCountry><contactTelephoneNumber>+49 7473 7585</contactTelephoneNumber><contactFaxNumber>+49 7473 6363</contactFaxNumber><contactVATidNumber>DE 201811244</contactVATidNumber><Kurzbezeichnung>Brielmann, Bern</Kurzbezeichnung><contactCustomerNumber>18564</contactCustomerNumber><contactBank>VR Bank Tübingen</contactBank><contactBankNumber>64061854</contactBankNumber><contactBankAccountNumber>40088</contactBankAccountNumber><contactIBAN>DE79 6406 1854 0000 0400 88</contactIBAN>