<contactNumber>720092</contactNumber><contactVendorNumber>720092</contactVendorNumber><K/I>I</K/I><contactName>Trensco GmbH & Co. KG</contactName><contactAddressStreet>Am Funkturm 9a</contactAddressStreet><contactAddressZipCode>29525</contactAddressZipCode><contactAddressCity>Uelzen</contactAddressCity><contactAddressCountry>Deutschland</contactAddressCountry><contactTelephoneNumber>+49 581 20839393</contactTelephoneNumber><contactFaxNumber>+49 581 3893275</contactFaxNumber><contactEmail>inf@trensco.de</contactEmail><contactVATidNumber>DE 338579135</contactVATidNumber><contactTAXidNumber>47200/04902</contactTAXidNumber><Kurzbezeichnung>Trensco GmbH & </Kurzbezeichnung><contactCustomerNumber>4815507</contactCustomerNumber><contactBank>Commerzbank Uelzen</contactBank><contactBankNumber>25840048</contactBankNumber><contactBankAccountNumber>560920100</contactBankAccountNumber><contactIBAN>DE06 2584 0048 0560 9201 00</contactIBAN>