<contactNumber>709401</contactNumber><contactVendorNumber>709401</contactVendorNumber><K/I>I</K/I><contactName>IFM Institut für Managementberatung</contactName><contactAddressStreet>Karl-Liebknecht-Straße 21/22</contactAddressStreet><contactAddressZipCode>14482</contactAddressZipCode><contactAddressCity>Potsdam</contactAddressCity><contactAddressCountry>Deutschland</contactAddressCountry><contactTelephoneNumber>+49 711 24791627</contactTelephoneNumber><contactEmail>info@ifm-business.de</contactEmail><contactVATidNumber>DE 157050817</contactVATidNumber><Kurzbezeichnung>IFM Institut fü</Kurzbezeichnung><contactCustomerNumber>64263</contactCustomerNumber><contactBank>Commerzbank Potsdam</contactBank><contactBankNumber>16040000</contactBankNumber><contactBankAccountNumber>138114400</contactBankAccountNumber><contactIBAN>DE78 1604 0000 0138 1144 00</contactIBAN>