<contactNumber>720041</contactNumber><contactVendorNumber>720041</contactVendorNumber><K/I>I</K/I><contactName>Total Walther GmbH tyco</contactName><contactAddressStreet>Tränkestraße 1</contactAddressStreet><contactAddressZipCode>70597</contactAddressZipCode><contactAddressCity>Stuttgart</contactAddressCity><contactAddressCountry>Deutschland</contactAddressCountry><contactTelephoneNumber>+49 711 72064-0</contactTelephoneNumber><contactFaxNumber>+49 711 72064-90</contactFaxNumber><contactEmail>more@truck.com</contactEmail><contactVATidNumber>DE 811169936</contactVATidNumber><Kurzbezeichnung>Total Walther G</Kurzbezeichnung><contactCustomerNumber>97947</contactCustomerNumber><contactBank>Deutsche Bank München</contactBank><contactBankNumber>70070010</contactBankNumber><contactBankAccountNumber>440112100</contactBankAccountNumber><contactIBAN>DE75 7007 0010 0440 1121 00</contactIBAN>