<contactNumber>717122</contactNumber><contactVendorNumber>717122</contactVendorNumber><K/I>I</K/I><contactName>SMI - Gräwe & Sohn GmbH</contactName><contactAddressStreet>Bahnhofstr. 44</contactAddressStreet><contactAddressZipCode>14774</contactAddressZipCode><contactAddressCity>Brandenburg an der Havel</contactAddressCity><contactAddressCountry>Deutschland</contactAddressCountry><contactTelephoneNumber>+49 3381 891334</contactTelephoneNumber><contactEmail>info@smi-office.de</contactEmail><contactVATidNumber>DE 294557662</contactVATidNumber><contactTAXidNumber>048/225/03044</contactTAXidNumber><Kurzbezeichnung>SMI - Gräwe & S</Kurzbezeichnung><contactCustomerNumber>219521</contactCustomerNumber><contactBank>Mittelbrandenbg Sparkasse</contactBank><contactBankNumber>16050000</contactBankNumber><contactBankAccountNumber>1000841037</contactBankAccountNumber><contactIBAN>DE91 1605 0000 1000 8410 37</contactIBAN>