<contactNumber>706501</contactNumber><contactVendorNumber>706501</contactVendorNumber><K/I>I</K/I><contactName>Flashbay Limited</contactName><contactAddressStreet>6 The Fountain Centre Imperial Wharf</contactAddressStreet><contactAddressCity>London SW6 2TW</contactAddressCity><contactAddressCountry>Großbritannien</contactAddressCountry><contactTelephoneNumber>+49 800 1004170</contactTelephoneNumber><contactVATidNumber>BE 0892001112</contactVATidNumber><Kurzbezeichnung>Flashbay Limite</Kurzbezeichnung><contactBank>Deutsche Bank PGK Detmold</contactBank><contactBankNumber>47670024</contactBankNumber><contactBankAccountNumber>403661200</contactBankAccountNumber><contactIBAN>DE39 4767 0024 0403 6612 00</contactIBAN>