<contactNumber>703221</contactNumber><contactVendorNumber>703221</contactVendorNumber><K/I>I</K/I><contactName>COLUMBUS McKINNON Engineered Products Gm</contactName><contactAddressStreet>Am Silberpark 2-8</contactAddressStreet><contactAddressZipCode>86438</contactAddressZipCode><contactAddressCity>Kissing</contactAddressCity><contactAddressCountry>Deutschland</contactAddressCountry><contactTelephoneNumber>+49 8233 2121-0</contactTelephoneNumber><contactFaxNumber>+49 8233 2121-805</contactFaxNumber><contactEmail>info.kissing@cmco.eu</contactEmail><contactVATidNumber>DE 205346027</contactVATidNumber><Kurzbezeichnung>COLUMBUS McKINN</Kurzbezeichnung><contactCustomerNumber>2070601</contactCustomerNumber><contactBank>UniCredit Bank-HypoVereinbk</contactBank><contactBankNumber>72020070</contactBankNumber><contactBankAccountNumber>359765410</contactBankAccountNumber><contactIBAN>DE24 7202 0070 0359 7654 10</contactIBAN>