<contactNumber>715041</contactNumber><contactVendorNumber>715041</contactVendorNumber><K/I>I</K/I><contactName>Peiner SMAG Lifting Technologies GmbH</contactName><contactAddressStreet>Windmühlenbergstraße 20-22</contactAddressStreet><contactAddressZipCode>38259</contactAddressZipCode><contactAddressCity>Salzgitter</contactAddressCity><contactAddressCountry>Deutschland</contactAddressCountry><contactTelephoneNumber>+49 5341 302-0</contactTelephoneNumber><contactFaxNumber>+49 5341 302-343</contactFaxNumber><contactEmail>Bettina.Heidemann@smag.de</contactEmail><contactVATidNumber>DE 293573990</contactVATidNumber><Kurzbezeichnung>Peiner SMAG Lif</Kurzbezeichnung><contactCustomerNumber>18298</contactCustomerNumber><contactBank>Commerzbank Braunschweig</contactBank><contactBankNumber>27040080</contactBankNumber><contactBankAccountNumber>590934600</contactBankAccountNumber><contactIBAN>DE73 2704 0080 0590 9346 00</contactIBAN>