<contactNumber>723541</contactNumber><contactVendorNumber>723541</contactVendorNumber><K/I>I</K/I><contactName>Winkler, Horst Montagebau GmbH</contactName><contactAddressStreet>Am Kalkoffen 5</contactAddressStreet><contactAddressZipCode>61206</contactAddressZipCode><contactAddressCity>Wöllstadt</contactAddressCity><contactAddressCountry>Deutschland</contactAddressCountry><contactTelephoneNumber>+49 6034 9188-0</contactTelephoneNumber><contactFaxNumber>+49 6034 9188-22</contactFaxNumber><contactEmail>info@winkler-montagebau.de</contactEmail><contactVATidNumber>DE 112614354</contactVATidNumber><contactTAXidNumber>2023580178</contactTAXidNumber><Kurzbezeichnung>Winkler, Horst</Kurzbezeichnung><contactBank>VB Mittelhessen</contactBank><contactBankNumber>51390000</contactBankNumber><contactBankAccountNumber>87230406</contactBankAccountNumber><contactIBAN>DE39 5139 0000 0087 2304 06</contactIBAN>