<contactNumber>703112</contactNumber><contactVendorNumber>703112</contactVendorNumber><K/I>I</K/I><contactName>Center4CNC GmbH & Co. KG</contactName><contactAddressStreet>Am Kornfeld 24</contactAddressStreet><contactAddressZipCode>86899</contactAddressZipCode><contactAddressCity>Landsberg am Lech</contactAddressCity><contactAddressCountry>Deutschland</contactAddressCountry><contactEmail>rechnung@center4cnc.de</contactEmail><contactVATidNumber>DE 254611637</contactVATidNumber><Kurzbezeichnung>Center4CNC GmbH</Kurzbezeichnung><contactCustomerNumber>143</contactCustomerNumber><contactBank>Stadtsparkasse München</contactBank><contactBankNumber>70150000</contactBankNumber><contactBankAccountNumber>87217725</contactBankAccountNumber><contactIBAN>DE32 7015 0000 0087 2177 25</contactIBAN>