<contactNumber>718361</contactNumber><contactVendorNumber>718361</contactVendorNumber><K/I>I</K/I><contactName>Schnirzer & Schöppe</contactName><contactAddressStreet>Marktstraße 7</contactAddressStreet><contactAddressZipCode>73779</contactAddressZipCode><contactAddressCity>Deizisau</contactAddressCity><contactAddressCountry>Deutschland</contactAddressCountry><contactTelephoneNumber>+49 7153 756-66</contactTelephoneNumber><contactFaxNumber>+49 7153 756-55</contactFaxNumber><contactTAXidNumber>5909260371</contactTAXidNumber><Kurzbezeichnung>Schnirzer & Sch</Kurzbezeichnung><contactBank>Volksbank Plochingen</contactBank><contactBankNumber>61191310</contactBankNumber><contactBankAccountNumber>704994003</contactBankAccountNumber><contactIBAN>DE87 6119 1310 0704 9940 03</contactIBAN>